algorand_vanity/generator.py
algorand_vanity-1.0.3.dist-info/LICENSE
algorand_vanity-1.0.3.dist-info/METADATA
algorand_vanity-1.0.3.dist-info/WHEEL
algorand_vanity-1.0.3.dist-info/entry_points.txt
algorand_vanity-1.0.3.dist-info/RECORD
