Metadata-Version: 2.1
Name: algorand-vanity
Version: 1.0.3
Summary: Vanity address generator for algorand wallets
Home-page: https://github.com/sithladyraven/algorand-vanity
License: MIT
Keywords: algorand,crypto,cryptocurrency,cryptowallet
Author: Kelsey Price
Author-email: contact@kelsey.dev
Requires-Python: >=3.8,<4.0
Classifier: License :: OSI Approved :: MIT License
Classifier: Programming Language :: Python :: 3
Classifier: Programming Language :: Python :: 3.8
Classifier: Programming Language :: Python :: 3.9
Classifier: Programming Language :: Python :: 3.10
Classifier: Programming Language :: Python :: 3.11
Requires-Dist: py-algorand-sdk (>=2.1.2,<3.0.0)
Requires-Dist: windows-curses (>=2.3.1,<3.0.0) ; sys_platform == "linux"
Project-URL: Repository, https://github.com/sithladyraven/algorand-vanity
